django_jalali_date_unfold-2.0.0.dist-info/licenses/LICENSE
jalali_date/__init__.py
jalali_date/admin.py
jalali_date/fields.py
jalali_date/settings.py
jalali_date/utils.py
jalali_date/widgets.py
jalali_date/static/admin/css/django_jalali.min.css
jalali_date/static/admin/js/django_jalali.min.js
jalali_date/templates/admin/jalali_change_form.html
jalali_date/templates/admin/edit_inline/jalali_stacked.html
jalali_date/templates/admin/edit_inline/jalali_tabular.html
jalali_date/templates/admin/includes/jalali_fieldset.html
jalali_date/templates/admin/widgets/jalali_split_datetime.html
jalali_date/templatetags/__init__.py
jalali_date/templatetags/jalali_tags.py
tests/__init__.py
tests/test_settings.py
tests/tests/__init__.py
tests/tests/templatetags/__init__.py
tests/tests/templatetags/test_jalali_admin_safe_readonly_template_tag.py
tests/tests/templatetags/test_jalali_now_template_tag.py
tests/tests/templatetags/test_to_jalali_template_tag.py
django_jalali_date_unfold-2.0.0.dist-info/METADATA
django_jalali_date_unfold-2.0.0.dist-info/WHEEL
django_jalali_date_unfold-2.0.0.dist-info/top_level.txt
django_jalali_date_unfold-2.0.0.dist-info/RECORD
